{"name":"TomEE","tagline":"TomEE is used by Adimpression","body":"# Driven by David Blevins, TomEE has evolved a lot since its baby stages. Adimpression proudly uses TomEE for most of its servers. \r\n\r\n## Why? \r\n\r\n### Because TomEE is pure Tomcat with Java EE capabilities\r\n### Because TomEE is open sourced\r\n### Because TomEE is well documented\r\n### Because TomEE is not messed up. Tomcat is taken clean and configured to be TomEE with minimal interference.\r\n### Because TomEE is fully Apache software\r\n\r\n## Where?\r\n\r\n### Is it Friday already? Look here then: [http://ThankGodItIsFriday.com](http://ThankGodItIsFriday.com)\r\n\r\n* On Facebook: [https://www.facebook.com/ThankGodItIsFriday](https://www.facebook.com/ThankGodItIsFriday)\r\n* On Twitter: [https://twitter.com/tgifteam](https://twitter.com/tgifteam)\r\n* On Wordpress: [http://tgifteam.wordpress.com](http://tgifteam.wordpress.com)\r\n* On Foursquare: [https://foursquare.com/tgifteam](https://foursquare.com/tgifteam)\r\n* On Google+: [https://plus.google.com/103812630775471841268](https://plus.google.com/103812630775471841268)\r\n","google":"UA-41791837-4","note":"Don't delete this file! It's used internally to help with page regeneration."}